fastapi_maintenance_mode/__init__.py
fastapi_maintenance_mode/main.py
fastapi_maintenance_mode/middleware.py
tests/__init__.py
tests/test_fastapi_maintenance_mode.py
fastapi_maintenance_mode-1.0.0.dist-info/LICENSE
fastapi_maintenance_mode-1.0.0.dist-info/METADATA
fastapi_maintenance_mode-1.0.0.dist-info/WHEEL
fastapi_maintenance_mode-1.0.0.dist-info/top_level.txt
fastapi_maintenance_mode-1.0.0.dist-info/RECORD
