Metadata-Version: 2.1
Name: fastapi-maintenance-mode
Version: 1.0.0
Summary: FastAPI middleware for enabling maintenance mode
Home-page: https://github.com/iunary/fastapi-maintenance-mode
Author: Yusuf
Author-email: contact@yusuf.im
License: MIT
Classifier: Framework :: FastAPI
Classifier: Intended Audience :: Developers
Classifier: License :: OSI Approved :: MIT License
Classifier: Programming Language :: Python :: 3
Classifier: Topic :: Internet :: WWW/HTTP :: HTTP Servers
License-File: LICENSE
Requires-Dist: fastapi
Requires-Dist: httpx
